plug_in/__init__.py
plug_in/boot/__init__.py
plug_in/boot/builder/__init__.py
plug_in/boot/builder/builder.py
plug_in/boot/builder/facade.py
plug_in/boot/builder/proto.py
plug_in/boot/builder/selector.py
plug_in/boot/root.py
plug_in/core/__init__.py
plug_in/core/asyncio/__init__.py
plug_in/core/asyncio/plugin.py
plug_in/core/enum.py
plug_in/core/host.py
plug_in/core/plug.py
plug_in/core/plugin.py
plug_in/core/registry.py
plug_in/exc/__init__.py
plug_in/ioc/__init__.py
plug_in/ioc/hosted_mark.py
plug_in/ioc/hosting.py
plug_in/ioc/parameter.py
plug_in/ioc/resolver.py
plug_in/ioc/router.py
plug_in/tools/__init__.py
plug_in/tools/introspect.py
plug_in/types/__init__.py
plug_in/types/alias.py
plug_in/types/proto/__init__.py
plug_in/types/proto/core_host.py
plug_in/types/proto/core_plug.py
plug_in/types/proto/core_plugin.py
plug_in/types/proto/core_registry.py
plug_in/types/proto/hosted_mark.py
plug_in/types/proto/joint.py
plug_in/types/proto/param_state.py
plug_in/types/proto/parameter.py
plug_in/types/proto/pluggable.py
plug_in/types/proto/resolver.py
plug_in/types/proto/router.py
pyplugin_lib-0.2.1.dist-info/LICENSE
pyplugin_lib-0.2.1.dist-info/METADATA
pyplugin_lib-0.2.1.dist-info/WHEEL
pyplugin_lib-0.2.1.dist-info/RECORD
