Metadata-Version: 2.1
Name: pyplugin-lib
Version: 0.2.1
Summary: Pythonic inversion of control targeting ports and adapters application development style
Home-page: https://github.com/igoras1993/plug-in
License: BSD-3-Clause
Keywords: plugins,adapters,ioc,di,dependency,injection
Author: kuta.0
Author-email: igor.kantorski@gmail.com
Requires-Python: >=3.12,<4.0
Classifier: Development Status :: 1 - Planning
Classifier: License :: OSI Approved :: BSD License
Classifier: Operating System :: OS Independent
Classifier: Programming Language :: Python :: 3
Classifier: Programming Language :: Python :: 3.12
Classifier: Topic :: Software Development :: Libraries
Classifier: Typing :: Typed
Project-URL: Documentation, https://github.com/igoras1993/plug-in
Project-URL: Repository, https://github.com/igoras1993/plug-in
